[{"playerServerId":3,"type":"ped","heading":223.62513732910157,"isReloading":false,"isRagdoll":false,"isInVehicle":false,"isWalking":false,"coords":{"z":107.48442840576172,"y":387.21484375,"x":202.0911407470703},"isDucking":false,"isInMeleeCombat":false,"isInCover":false,"currentAnimation":0.0,"isRunning":false,"pedId":5,"weapon":453432689,"isAiming":false},{"playerServerId":-1,"type":"ped","heading":223.62513732910157,"isReloading":false,"isRagdoll":false,"isInVehicle":false,"isWalking":false,"coords":{"z":107.48442840576172,"y":387.21484375,"x":202.0911407470703},"isDucking":false,"isInMeleeCombat":false,"isInCover":false,"currentAnimation":0.0,"isRunning":false,"pedId":5,"weapon":453432689,"isAiming":false}]